signalprocessing/__init__.py
signalprocessing/basicdspalgorithm.py
signalprocessing/fir.py
signalprocessing/sample.py
signalprocessing-0.212.dist-info/METADATA
signalprocessing-0.212.dist-info/WHEEL
signalprocessing-0.212.dist-info/top_level.txt
signalprocessing-0.212.dist-info/RECORD
