Metadata-Version: 2.1
Name: signalprocessing
Version: 0.212
Summary: Basic Signal processing and Fir filterdesign
Home-page: https://github.com/shivarao101/signalprocessing
Author: shivaprasad
Author-email: shivarao101@gmail.com
License: MIT
Download-URL: https://github.com/shivarao101/signalprocessing/archive/0.212.tar.gz
Keywords: CONV,FFT,FIR,LP,HP
Platform: UNKNOWN
Classifier: Development Status :: 3 - Alpha
Classifier: Intended Audience :: Developers
Classifier: Topic :: Software Development :: Build Tools
Classifier: License :: OSI Approved :: MIT License
Classifier: Programming Language :: Python :: 2.7
Classifier: Programming Language :: Python :: 3.4
Classifier: Programming Language :: Python :: 3.5
Classifier: Programming Language :: Python :: 3.6
Requires-Dist: matplotlib
